<?xml version="1.0" encoding="UTF-8"?><record_update table="sp_instance">
    <sp_instance action="DELETE">
        <active>true</active>
        <class_name/>
        <color>primary</color>
        <css/>
        <glyph/>
        <id/>
        <order>1</order>
        <roles/>
        <short_description/>
        <size>md</size>
        <sp_column display_value="2">8fc4cc88470831106e504aff336d432f</sp_column>
        <sp_widget display_value="link-button">abc50de6d702120023c84f80de61036a</sp_widget>
        <sys_class_name>sp_instance</sys_class_name>
        <sys_created_by>shanmugapriyat@vuram.com</sys_created_by>
        <sys_created_on>2023-07-07 13:08:25</sys_created_on>
        <sys_id>ae06694347bf21106e504aff336d431b</sys_id>
        <sys_mod_count>10</sys_mod_count>
        <sys_name/>
        <sys_package display_value="LCMS" source="x_1025229_lcms">0d775003473261106e504aff336d43a7</sys_package>
        <sys_policy/>
        <sys_scope display_value="LCMS">0d775003473261106e504aff336d43a7</sys_scope>
        <sys_update_name>sp_instance_ae06694347bf21106e504aff336d431b</sys_update_name>
        <sys_updated_by>admin</sys_updated_by>
        <sys_updated_on>2023-07-10 08:38:45</sys_updated_on>
        <title/>
        <url/>
        <widget_parameters><![CDATA[{
	"href": {
		"value": "https://dev167757.service-now.com/cms?id=admin_form&table=sys_choice",
		"displayValue": "https://dev167757.service-now.com/cms?id=admin_form&table=sys_choice"
	},
	"button_text": {
		"value": "Add a Choice in request table",
		"displayValue": "Add a Choice in request table"
	}
}]]></widget_parameters>
    </sp_instance>
    <sys_translated_text action="DELETE" query="documentkey=ae06694347bf21106e504aff336d431b"/>
    <sys_update_version action="INSERT_OR_UPDATE">
        <action>DELETE</action>
        <application display_value="LCMS">0d775003473261106e504aff336d43a7</application>
        <file_path/>
        <instance_id>f4b0afb0dbf92950dc3fc597059619ab</instance_id>
        <instance_name>dev167757</instance_name>
        <name>sp_instance_ae06694347bf21106e504aff336d431b</name>
        <payload>&lt;?xml version="1.0" encoding="UTF-8"?&gt;&lt;record_update table="sp_instance"&gt;&lt;sp_instance action="INSERT_OR_UPDATE"&gt;&lt;active&gt;true&lt;/active&gt;&lt;class_name/&gt;&lt;color&gt;primary&lt;/color&gt;&lt;css/&gt;&lt;glyph/&gt;&lt;id/&gt;&lt;order&gt;1&lt;/order&gt;&lt;roles/&gt;&lt;short_description/&gt;&lt;size&gt;md&lt;/size&gt;&lt;sp_column display_value="2"&gt;8fc4cc88470831106e504aff336d432f&lt;/sp_column&gt;&lt;sp_widget display_value="link-button"&gt;abc50de6d702120023c84f80de61036a&lt;/sp_widget&gt;&lt;sys_class_name&gt;sp_instance&lt;/sys_class_name&gt;&lt;sys_created_by&gt;shanmugapriyat@vuram.com&lt;/sys_created_by&gt;&lt;sys_created_on&gt;2023-07-07 13:08:25&lt;/sys_created_on&gt;&lt;sys_id&gt;ae06694347bf21106e504aff336d431b&lt;/sys_id&gt;&lt;sys_mod_count&gt;10&lt;/sys_mod_count&gt;&lt;sys_name/&gt;&lt;sys_package display_value="LCMS" source="x_1025229_lcms"&gt;0d775003473261106e504aff336d43a7&lt;/sys_package&gt;&lt;sys_policy/&gt;&lt;sys_scope display_value="LCMS"&gt;0d775003473261106e504aff336d43a7&lt;/sys_scope&gt;&lt;sys_update_name&gt;sp_instance_ae06694347bf21106e504aff336d431b&lt;/sys_update_name&gt;&lt;sys_updated_by&gt;admin&lt;/sys_updated_by&gt;&lt;sys_updated_on&gt;2023-07-10 08:38:45&lt;/sys_updated_on&gt;&lt;title/&gt;&lt;url/&gt;&lt;widget_parameters&gt;&lt;![CDATA[{
	"href": {
		"value": "https://dev167757.service-now.com/cms?id=admin_form&amp;table=sys_choice",
		"displayValue": "https://dev167757.service-now.com/cms?id=admin_form&amp;table=sys_choice"
	},
	"button_text": {
		"value": "Add a Choice in request table",
		"displayValue": "Add a Choice in request table"
	}
}]]&gt;&lt;/widget_parameters&gt;&lt;/sp_instance&gt;&lt;sys_translated_text action="delete_multiple" query="documentkey=ae06694347bf21106e504aff336d431b"/&gt;&lt;/record_update&gt;</payload>
        <payload_hash>-1081854848</payload_hash>
        <record_name/>
        <reverted_from/>
        <source>a6e66ce8478721106e504aff336d4382</source>
        <source_table>sys_update_set</source_table>
        <state>previous</state>
        <sys_created_by>admin</sys_created_by>
        <sys_created_on>2023-07-10 08:38:45</sys_created_on>
        <sys_id>5d1548c8470831106e504aff336d4316</sys_id>
        <sys_mod_count>0</sys_mod_count>
        <sys_recorded_at>1893ef3fe610000001</sys_recorded_at>
        <sys_updated_by>admin</sys_updated_by>
        <sys_updated_on>2023-07-10 08:38:45</sys_updated_on>
        <type>Instance</type>
        <update_guid>d11548c811083110f44aaec0718ca316</update_guid>
        <update_guid_history>d11548c811083110f44aaec0718ca316:-1081854848,59154888070831107bf156e564c00811:-415268561,690584c8b0083110db399f3d50bebdb3:-1081854848,e105888854083110223b811e77c7f2f8:1281623888,dd0544c87a083110bbc9561dde986374:-1081854848,700500c8ac083110f9a1eca81e481534:1281623888,221ef77f05f7211076185141aff20b72:-415268561,c94a65cbc6bf211043f5a3f7a10bbe4a:-576941165,5b2ae1cbcbbf2110152bb063ab02bb13:1692360146,b82665c3c0bf2110bd212c2dce80393d:2031761712,a20661c334bf21108e9d40f3cb59ae9a:-1832859311</update_guid_history>
    </sys_update_version>
    <sys_metadata_delete action="INSERT_OR_UPDATE">
        <sys_audit_delete display_value="">c82588c8470831106e504aff336d4399</sys_audit_delete>
        <sys_class_name>sys_metadata_delete</sys_class_name>
        <sys_created_by>admin</sys_created_by>
        <sys_created_on>2023-07-10 08:38:55</sys_created_on>
        <sys_db_object display_value="" name="sp_instance">sp_instance</sys_db_object>
        <sys_id>adaa0ca65cbb421b829f030712434999</sys_id>
        <sys_metadata>ae06694347bf21106e504aff336d431b</sys_metadata>
        <sys_mod_count>0</sys_mod_count>
        <sys_name/>
        <sys_package display_value="LCMS" source="x_1025229_lcms">0d775003473261106e504aff336d43a7</sys_package>
        <sys_parent/>
        <sys_policy/>
        <sys_scope display_value="LCMS">0d775003473261106e504aff336d43a7</sys_scope>
        <sys_scope_delete display_value="">0019f46a57bd4d24a3bc5dcd12034310</sys_scope_delete>
        <sys_update_name>sp_instance_ae06694347bf21106e504aff336d431b</sys_update_name>
        <sys_update_version display_value="sp_instance_ae06694347bf21106e504aff336d431b">5d1548c8470831106e504aff336d4316</sys_update_version>
        <sys_updated_by>admin</sys_updated_by>
        <sys_updated_on>2023-07-10 08:38:55</sys_updated_on>
    </sys_metadata_delete>
</record_update>
